.gitignore
CMakeLists.txt
MANIFEST.in
README.rst
setup.py
test_cython/__init__.py
test_cython/approxe.c
test_cython/approxe.pyx
test_cython/dot_cython.c
test_cython/dot_cython.pyx
test_cython/test.py
test_cython/version.py
test_pybind/CMakeLists.txt
test_pybind/__init__.py
test_pybind/account.cpp
test_pybind/account.hpp
test_pybind/version.py
test_pybind.egg-info/PKG-INFO
test_pybind.egg-info/SOURCES.txt
test_pybind.egg-info/dependency_links.txt
test_pybind.egg-info/top_level.txt